b2upload/__init__.py
b2upload/b2upload.py
b2upload/command_line.py
b2upload-0.1.9.dist-info/DESCRIPTION.rst
b2upload-0.1.9.dist-info/METADATA
b2upload-0.1.9.dist-info/RECORD
b2upload-0.1.9.dist-info/WHEEL
b2upload-0.1.9.dist-info/entry_points.txt
b2upload-0.1.9.dist-info/metadata.json
b2upload-0.1.9.dist-info/top_level.txt
